{
  "15181": "Goblin Guard",
  "16609": "Goblin Sword",
  "16636": "Goblin Crossbow",
  "16637": "Goblin Crossbow",
  "16638": "Goblin Cudgel",
  "16639": "Goblin Cudgel",
  "16640": "Goblin Crossbow",
  "16647": "Goblin Sword",
  "16650": "Goblin Cudgel",
  "16656": "Goblin Crossbow",
  "16694": "Goblin Sword",
  "16695": "Goblin Sword",
  "16698": "Goblin Crossbow",
  "16699": "Goblin Crossbow",
  "16700": "Goblin Crossbow",
  "16701": "Goblin Crossbow",
  "16702": "Goblin Crossbow",
  "16703": "Goblin Crossbow",
  "16704": "Goblin Sword",
  "16705": "Goblin Sword",
  "16706": "Goblin Sword",
  "16707": "Goblin Cudgel",
  "16708": "Goblin Cudgel",
  "16710": "Goblin Cudgel",
  "16714": "Goblin Sword",
  "16717": "Goblin Sword",
  "16718": "Goblin Sword",
  "16719": "Goblin Sword",
  "16720": "Goblin Sword",
  "16721": "Goblin Sword",
  "16722": "Goblin Sword",
  "16723": "Goblin Sword",
  "16724": "Goblin Sword",
  "16725": "Goblin Sword",
  "16731": "Goblin Crossbow",
  "16732": "Goblin Crossbow",
  "16733": "Goblin Crossbow",
  "16734": "Goblin Crossbow",
  "16735": "Goblin Crossbow",
  "16736": "Goblin Crossbow",
  "16737": "Goblin Crossbow",
  "16738": "Goblin Crossbow",
  "16740": "Goblin Crossbow",
  "16741": "Goblin Cudgel",
  "16746": "Goblin Cudgel",
  "16748": "Goblin Cudgel",
  "17231": "Goblin Cudgel",
  "17232": "Goblin Sword",
  "17234": "Goblin Crossbow",
  "17235": "Goblin Crossbow",
  "17236": "Goblin Crossbow",
  "17240": "Goblin Crossbow"
}